jieba_htsc/__init__.py
jieba_htsc/cut.py
jieba_htsc/cut_for_search.py
jieba_htsc-1.0.dist-info/DESCRIPTION.rst
jieba_htsc-1.0.dist-info/METADATA
jieba_htsc-1.0.dist-info/RECORD
jieba_htsc-1.0.dist-info/WHEEL
jieba_htsc-1.0.dist-info/metadata.json
jieba_htsc-1.0.dist-info/top_level.txt
