Metadata-Version: 2.0
Name: jieba-htsc
Version: 1.0
Summary: jieba_new
Home-page: UNKNOWN
Author: QJJ
Author-email: liqiong_water@126.com
License: seu
Platform: UNKNOWN
